datastore_entity/__about__.py
datastore_entity/__init__.py
datastore_entity/datastore_entity.py
datastore_entity/entity_value.py
datastore_entity-0.2.0.dist-info/LICENSE
datastore_entity-0.2.0.dist-info/METADATA
datastore_entity-0.2.0.dist-info/WHEEL
datastore_entity-0.2.0.dist-info/top_level.txt
datastore_entity-0.2.0.dist-info/RECORD
