Metadata-Version: 2.1
Name: datastore-entity
Version: 0.2.0
Summary: A simple ORM-like interface to Google Cloud NoSQL Datastore
Home-page: https://github.com/komlasapaty/datastore-entity
Author: Seyram Komla Sapaty
Author-email: komlasapaty@gmail.com
License: UNKNOWN
Platform: UNKNOWN
Classifier: Programming Language :: Python :: 3
Classifier: License :: OSI Approved :: MIT License
Classifier: Operating System :: OS Independent
Classifier: Topic :: Internet :: WWW/HTTP :: Dynamic Content
Classifier: Topic :: Software Development :: Libraries :: Python Modules
Requires-Python: >=3.5
Requires-Dist: google-cloud-datastore (>=1)
